pytest_gitcov/__init__.py
pytest_gitcov/coverage.py
pytest_gitcov/git.py
pytest_gitcov/plugin.py
pytest_gitcov/report.py
pytest_gitcov-0.1.5.data/scripts/git-py-coverage
pytest_gitcov-0.1.5.dist-info/LICENSE
pytest_gitcov-0.1.5.dist-info/METADATA
pytest_gitcov-0.1.5.dist-info/WHEEL
pytest_gitcov-0.1.5.dist-info/entry_points.txt
pytest_gitcov-0.1.5.dist-info/top_level.txt
pytest_gitcov-0.1.5.dist-info/RECORD
