Metadata-Version: 2.1
Name: pytest-gitcov
Version: 0.1.5
Summary: Pytest plugin for reporting on coverage of the last git commit.
Home-page: https://github.com/machshev/pytest-gitcov
Author: David James McCorrie
Author-email: djmccorrie@gmail.com
License: MIT
Platform: UNKNOWN
Classifier: Development Status :: 2 - Pre-Alpha
Classifier: Framework :: Pytest
Classifier: Intended Audience :: Developers
Classifier: License :: OSI Approved :: MIT License
Classifier: Natural Language :: English
Classifier: Operating System :: POSIX :: Linux
Classifier: Programming Language :: Python :: 3
Classifier: Topic :: Software Development :: Testing
Requires-Dist: pytest-cov
Requires-Dist: coverage
